jupyter_advanced_latex/__init__.py
jupyter_advanced_latex/magics.py
jupyter_advanced_latex/js/jquery.min.js
jupyter_advanced_latex/js/plastex.js
jupyter_advanced_latex/js/svgxuse.js
jupyter_advanced_latex/styles/theme-blue.css
jupyter_advanced_latex/styles/theme-green.css
jupyter_advanced_latex/styles/theme-white.css
jupyter_advanced_latex-0.1.1.dist-info/METADATA
jupyter_advanced_latex-0.1.1.dist-info/WHEEL
jupyter_advanced_latex-0.1.1.dist-info/licenses/LICENSE
jupyter_advanced_latex-0.1.1.dist-info/RECORD
