Metadata-Version: 2.4
Name: jupyter-advanced-latex
Version: 0.1.1
Summary: IPython magic commands for advanced LaTeX rendering via plasTeX, providing support for displaying tables and figures as HTML.
Project-URL: Homepage, https://github.com/jiboncom/jupyter-advanced-latex
Project-URL: Issues, https://github.com/jiboncom/jupyter-advanced-latex/issues
Author-email: Javier Boncompte <jiboncom@gmail.com>
License: Apache 2.0
License-File: LICENSE
Keywords: ipython,jupyter,latex,magics,plastex
Classifier: Framework :: Jupyter
Classifier: Intended Audience :: Science/Research
Classifier: License :: OSI Approved :: Apache Software License
Classifier: Programming Language :: Python :: 3
Classifier: Programming Language :: Python :: 3 :: Only
Classifier: Topic :: Text Processing :: Markup :: LaTeX
Requires-Python: >=3.9
Requires-Dist: plastex>=3.1
